{
  "adapter_status": "pond_backed",
  "bounded_synthesis": "Observed: pond/proof recall returned 5 motifs and 10 lineage refs; 6 contradiction warnings and 5 unresolved tensions remain visible. Inferred: the safe next...",
  "claim_boundary_audit": [
    {
      "boundary_risk": "low",
      "evidence_refs": [
        "request_visible_ref:proofs/023-truth-reconstruction-challenge-002/baseline/source_index.json",
        "request_visible_ref:proofs/023-truth-reconstruction-challenge-002/baseline/baseline_truth_map.json"
      ],
      "id": "audit.public_private_boundary",
      "message": "Only public-safe summaries, scores, refs, warnings, and hashes are exposed.",
      "reason_codes": [
        "PUBLIC_PRIVATE_BOUNDARY",
        "NO_HIDDEN_REASONING_EXPOSED"
      ],
      "status": "pass"
    }
  ],
  "claim_pressure": [
    {
      "boundary_risk": "medium",
      "evidence_refs": [
        "artifacts/inside_voice/continuity_arbitration/continuity_arbitration_report.json"
      ],
      "id": "contradiction:400f6de8bc04",
      "pressure_score": 0.5,
      "warning": "CONFLICTING_PATHWAY_REINFORCEMENT"
    }
  ],
  "confidence": "medium",
  "contribution_grade": "bounded",
  "contribution_grade_details": {
    "contribution_grade": "bounded",
    "grade_reasons": [
      "refs_motifs_tensions_and_pressure_present"
    ],
    "minimum_gate_passed": true
  },
  "findings": [
    {
      "claim": "Consultation is bounded to the supplied request envelope and local contract schema.",
      "confidence": "high",
      "evidence": [
        "mode:synthesis",
        "files:7",
        "constraints:8",
        "desired_artifacts:5"
      ],
      "id": "mcp.contract.bounds",
      "lineage_refs": [
        "884434a297131ceea0c253ce65fbe971c4e5b5acc46f4df97cbfb65f2eda98a5"
      ],
      "risk": "low"
    }
  ],
  "gate_failures": [],
  "lineage": {
    "request_hash": "884434a297131ceea0c253ce65fbe971c4e5b5acc46f4df97cbfb65f2eda98a5",
    "response_hash": "606c3f4d01e8cd8ad3580f7e3eaf08fbba8bae4f4ad13e3a2ec7cea246e3c8db",
    "runtime": {
      "corpus_hash": "9dc990b92a07a9c77beafae5036894225983ce47f5fd2c6650266d29afc81b15",
      "runtime_request_hash": "884434a297131ceea0c253ce65fbe971c4e5b5acc46f4df97cbfb65f2eda98a5",
      "runtime_response_hash": "33498177e27f524be1fac7ba64dc9c99fe92a7e157684b30d4d88f9e16593de8",
      "schema_version": "belief_ledger.inside_voice_runtime.v1"
    },
    "source_refs": [
      "request_id:sha256:641f00279cc2acff",
      "task:sha256:ab9ff4a8efcdb196"
    ]
  },
  "lineage_refs": [
    "artifacts/pond/mcp_seasoned_first_principles_admitted.jsonl#19",
    "request_visible_ref:proofs/023-truth-reconstruction-challenge-002/baseline/source_index.json",
    "request_visible_ref:proofs/023-truth-reconstruction-challenge-002/baseline/baseline_truth_map.json"
  ],
  "mode": "synthesis",
  "operational_boundaries": [],
  "pressure_rankings": [
    {
      "boundary_risk": "medium",
      "claim_level": "unresolved",
      "id": "pressure:44eeb320a80c1c5f",
      "kind": "unresolved",
      "pressure_reasons": [
        "DIRECT_REQUEST_MATCH",
        "CONTRADICTION_RELEVANCE",
        "CLAIM_DISCIPLINE_RELEVANCE"
      ],
      "pressure_score": 0.878,
      "reason_codes": [
        "CONTRADICTION_CLUSTER",
        "CONFLICTING_PATHWAY_REINFORCEMENT",
        "DIRECT_REQUEST_MATCH",
        "CONTRADICTION_RELEVANCE"
      ],
      "source_ref": "artifacts/inside_voice/continuity_arbitration/continuity_arbitration_report.json",
      "supporting_refs": [
        "artifacts/inside_voice/continuity_arbitration/continuity_arbitration_report.json"
      ],
      "title": "CONFLICTING_PATHWAY_REINFORCEMENT"
    },
    {
      "boundary_risk": "medium",
      "claim_level": "unresolved",
      "id": "pressure:cf4e82e380cf1a94",
      "kind": "unresolved",
      "pressure_reasons": [
        "DIRECT_REQUEST_MATCH",
        "PROOF_BOUNDARY_RELEVANCE",
        "CONTRADICTION_RELEVANCE"
      ],
      "pressure_score": 0.872,
      "reason_codes": [
        "TASK_PATHWAY_COLLISION",
        "DIRECT_REQUEST_MATCH",
        "PROOF_BOUNDARY_RELEVANCE",
        "CONTRADICTION_RELEVANCE"
      ],
      "source_ref": "artifacts/inside_voice/continuity_arbitration/continuity_arbitration_report.json",
      "supporting_refs": [
        "artifacts/inside_voice/continuity_arbitration/continuity_arbitration_report.json",
        "6a8a6591e9487b92e32491390a3edca614b4ce3b046e81264a7f321fe59f66ee"
      ],
      "title": "arbitration:28663be18db91b7d"
    },
    {
      "boundary_risk": "medium",
      "claim_level": "inferred",
      "id": "pressure:1fb02e9c60565a25",
      "kind": "unresolved",
      "pressure_reasons": [
        "DIRECT_REQUEST_MATCH",
        "PROOF_BOUNDARY_RELEVANCE",
        "CONTRADICTION_RELEVANCE"
      ],
      "pressure_score": 0.859,
      "reason_codes": [
        "MCP_SEASONED_CANDIDATE",
        "ORIGINAL_CANDIDATE_SCAFFOLD_ONLY",
        "MCP_POND_BACKED_BATCH_PASSED",
        "MCP_RUNTIME_HASH_PRESENT"
      ],
      "source_ref": "artifacts/pond/mcp_seasoned_first_principles_admitted.jsonl#45",
      "supporting_refs": [
        "artifacts/pond/mcp_seasoned_first_principles_admitted.jsonl#45",
        "artifacts/pond/first_principles_seasoning_corpus.jsonl#fp_0046"
      ],
      "title": "fp_lineage_candidate_0046"
    }
  ],
  "recalled_motifs": [
    {
      "boundary_risk": "medium",
      "motif": "fp_lineage_candidate_0050",
      "motif_id": "inside_voice_runtime:6618eceaa43863e083b2",
      "pressure_score": 0.639
    }
  ],
  "recommendations": [
    {
      "action": "Retry with a larger max_output_chars value.",
      "blocking": false,
      "id": "mcp.rec.raise_output_limit",
      "reason": "Full pond-backed response exceeded the requested output bound."
    }
  ],
  "recommended_next_pressure": [
    "Inspect the cited proof and claim-boundary artifacts before using the synthesis as task evidence.",
    "Preserve observed/inferred/hypothesis/unresolved labels in any downstream response."
  ],
  "recommended_validation": [
    "Inspect the cited proof and claim-boundary artifacts before using the synthesis as task evidence.",
    "Preserve observed/inferred/hypothesis/unresolved labels in any downstream response."
  ],
  "relevant_lineage_refs": [
    "artifacts/pond/mcp_seasoned_first_principles_admitted.jsonl#19",
    "request_visible_ref:proofs/023-truth-reconstruction-challenge-002/baseline/source_index.json",
    "request_visible_ref:proofs/023-truth-reconstruction-challenge-002/baseline/baseline_truth_map.json"
  ],
  "request_id": "proof-023-truth-reconstruction-002-consult-004-csi",
  "retrieved_artifact_refs": [
    "artifacts/pond/mcp_seasoned_first_principles_admitted.jsonl#19",
    "artifacts/pond/mcp_seasoned_first_principles_admitted.jsonl#49",
    "artifacts/pond/mcp_seasoned_reusable_lineage_candidates.jsonl#49"
  ],
  "runtime_stage_report_ref": "artifacts/integrations/inside_voice_runtime/runtime_stage_report.json",
  "summary": "Consultation output was compacted to honor max_output_chars.",
  "uncertainty": [
    "OUTPUT_COMPACTED_TO_MAX_OUTPUT_CHARS",
    "Recall is bounded to indexed local pond/proof artifacts and may miss evidence outside the declared corpus.",
    "Recalled reports remain evidence, not implementation capability."
  ],
  "unresolved_tensions": [
    {
      "boundary_risk": "medium",
      "evidence_refs": [
        "artifacts/inside_voice/epistemic_gap/epistemic_gap_requests.jsonl#0"
      ],
      "id": "inside_voice_runtime:d43e2e09c028b98314e8",
      "pressure_score": 0.854,
      "status": "unresolved",
      "tension": "gap:5c482ea64982398d"
    }
  ],
  "verdict": "ok"
}