{
  "records": [
    {
      "cues": [
        "arrival",
        "backlog",
        "bottleneck",
        "channel",
        "choke",
        "decline",
        "flow",
        "input",
        "lane",
        "narrow",
        "origin",
        "output",
        "passage",
        "path",
        "pipe",
        "queue",
        "resistance",
        "restriction",
        "route",
        "source",
        "supply",
        "throat",
        "throughput",
        "upstream",
        "water"
      ],
      "lesson_text": "ACTION: SEASON. Mechanism label: FLOW. Jobs originate at workstations, pass through a spool route, and emerge in bursts when release is metered. Season FLOW from printer_spool_density_01 for Proof 036 level 1.",
      "lineage_hash": "137b0fbd2415e504e482c5d53b7f17b40e5c15a94f0a29928a897b4c90ac9675",
      "lineage_payload": {
        "cues": [
          "flow",
          "route"
        ],
        "lesson_text": "ACTION: SEASON. Mechanism label: FLOW. Jobs originate at workstations, pass through a spool route, and emerge in bursts when release is metered. Season FLOW from printer_spool_density_01 for Proof 036 level 1.",
        "mechanism": "FLOW",
        "motifs": [
          "Source",
          "Path",
          "Resistance",
          "Flow"
        ],
        "payload_hash": "fc42c098ec0e731f61f4f75c8d2be0df0ca1c9e8bc6a9095178946ddb491cdfe",
        "request_id": "proof-036-level-1-season-006-flow",
        "source_refs": [
          "request",
          "context.summary"
        ]
      },
      "mechanism": "FLOW",
      "motifs": [
        "Source",
        "Path",
        "Resistance",
        "Flow"
      ],
      "record_id": "pond:flow:137b0fbd2415e504"
    },
    {
      "cues": [
        "arrival",
        "backlog",
        "bottleneck",
        "channel",
        "choke",
        "decline",
        "flow",
        "input",
        "lane",
        "narrow",
        "origin",
        "output",
        "passage",
        "path",
        "pipe",
        "queue",
        "resistance",
        "restriction",
        "route",
        "source",
        "supply",
        "throat",
        "throughput",
        "upstream",
        "water"
      ],
      "lesson_text": "ACTION: SEASON. Mechanism label: FLOW. People arrive at a desk, pass one review lane, and wait when the lane constricts arrivals to later appointments. Season FLOW from clinic_checkin_density_01 for Proof 036 level 1.",
      "lineage_hash": "196e365e31a887595cf25742393619c5eb6c0ebe5784071d5401f6519539fbc7",
      "lineage_payload": {
        "cues": [
          "arrival",
          "flow",
          "lane"
        ],
        "lesson_text": "ACTION: SEASON. Mechanism label: FLOW. People arrive at a desk, pass one review lane, and wait when the lane constricts arrivals to later appointments. Season FLOW from clinic_checkin_density_01 for Proof 036 level 1.",
        "mechanism": "FLOW",
        "motifs": [
          "Source",
          "Path",
          "Resistance",
          "Flow"
        ],
        "payload_hash": "fedea1ca5f1e8a29811a8fa57b26847c7ca2af29d6bc0da4dbd2b0813d82eb1c",
        "request_id": "proof-036-level-1-season-002-flow",
        "source_refs": [
          "request",
          "context.summary"
        ]
      },
      "mechanism": "FLOW",
      "motifs": [
        "Source",
        "Path",
        "Resistance",
        "Flow"
      ],
      "record_id": "pond:flow:196e365e31a88759"
    },
    {
      "cues": [
        "arrival",
        "backlog",
        "bottleneck",
        "channel",
        "choke",
        "decline",
        "flow",
        "input",
        "lane",
        "narrow",
        "origin",
        "output",
        "passage",
        "path",
        "pipe",
        "queue",
        "resistance",
        "restriction",
        "route",
        "source",
        "supply",
        "throat",
        "throughput",
        "upstream",
        "water"
      ],
      "lesson_text": "ACTION: SEASON. Mechanism label: FLOW. Samples enter accessioning, move through a handoff lane, and starve analysis benches when verification narrows. Season FLOW from lab_samples_density_01 for Proof 036 level 1.",
      "lineage_hash": "2f12d089076b6e6b801586fe0e6ae5c1024f5dafb2d3585055b5267ae5eac33e",
      "lineage_payload": {
        "cues": [
          "flow",
          "lane",
          "narrow"
        ],
        "lesson_text": "ACTION: SEASON. Mechanism label: FLOW. Samples enter accessioning, move through a handoff lane, and starve analysis benches when verification narrows. Season FLOW from lab_samples_density_01 for Proof 036 level 1.",
        "mechanism": "FLOW",
        "motifs": [
          "Source",
          "Path",
          "Resistance",
          "Flow"
        ],
        "payload_hash": "96d152da5dc060fac10a5842d44fe66095d547ffb6f7b80586af819b692afc7b",
        "request_id": "proof-036-level-1-season-007-flow",
        "source_refs": [
          "request",
          "context.summary"
        ]
      },
      "mechanism": "FLOW",
      "motifs": [
        "Source",
        "Path",
        "Resistance",
        "Flow"
      ],
      "record_id": "pond:flow:2f12d089076b6e6b"
    },
    {
      "cues": [
        "arrival",
        "backlog",
        "bottleneck",
        "channel",
        "choke",
        "decline",
        "flow",
        "input",
        "lane",
        "narrow",
        "origin",
        "output",
        "passage",
        "path",
        "pipe",
        "queue",
        "resistance",
        "restriction",
        "route",
        "source",
        "supply",
        "throat",
        "throughput",
        "upstream",
        "water"
      ],
      "lesson_text": "ACTION: SEASON. Mechanism label: FLOW. Trays move along a counter passage, a single payment throat limits passage, and diners wait before seating. Season FLOW from cafeteria_line_density_01 for Proof 036 level 1.",
      "lineage_hash": "3fe21f18de3ea9a3ec6ce46aeb10b4b669550f0cc59034c8c2a69f1d3a31bc74",
      "lineage_payload": {
        "cues": [
          "flow",
          "passage",
          "throat"
        ],
        "lesson_text": "ACTION: SEASON. Mechanism label: FLOW. Trays move along a counter passage, a single payment throat limits passage, and diners wait before seating. Season FLOW from cafeteria_line_density_01 for Proof 036 level 1.",
        "mechanism": "FLOW",
        "motifs": [
          "Source",
          "Path",
          "Resistance",
          "Flow"
        ],
        "payload_hash": "e647cc412de91884dad6d66d02dfa2b7e55ec050343789476ce9df9882270d33",
        "request_id": "proof-036-level-1-season-005-flow",
        "source_refs": [
          "request",
          "context.summary"
        ]
      },
      "mechanism": "FLOW",
      "motifs": [
        "Source",
        "Path",
        "Resistance",
        "Flow"
      ],
      "record_id": "pond:flow:3fe21f18de3ea9a3"
    },
    {
      "cues": [
        "arrival",
        "backlog",
        "bottleneck",
        "channel",
        "choke",
        "decline",
        "flow",
        "input",
        "lane",
        "narrow",
        "origin",
        "output",
        "passage",
        "path",
        "pipe",
        "queue",
        "resistance",
        "restriction",
        "route",
        "source",
        "supply",
        "throat",
        "throughput",
        "upstream",
        "water"
      ],
      "lesson_text": "ACTION: SEASON. Mechanism label: FLOW. Riders start at a concourse, pass a stair throat, and arrive sparsely at the platform when the throat narrows. Season FLOW from train_platform_density_01 for Proof 036 level 1.",
      "lineage_hash": "449cb1d71565af19ff92e3ff4c4751e23802e54b3793380184c77affbcf596a5",
      "lineage_payload": {
        "cues": [
          "flow",
          "narrow",
          "throat"
        ],
        "lesson_text": "ACTION: SEASON. Mechanism label: FLOW. Riders start at a concourse, pass a stair throat, and arrive sparsely at the platform when the throat narrows. Season FLOW from train_platform_density_01 for Proof 036 level 1.",
        "mechanism": "FLOW",
        "motifs": [
          "Source",
          "Path",
          "Resistance",
          "Flow"
        ],
        "payload_hash": "a161a5920af96438a4f3065f052f51a27f966346b110e95a9f33857ac435e314",
        "request_id": "proof-036-level-1-season-010-flow",
        "source_refs": [
          "request",
          "context.summary"
        ]
      },
      "mechanism": "FLOW",
      "motifs": [
        "Source",
        "Path",
        "Resistance",
        "Flow"
      ],
      "record_id": "pond:flow:449cb1d71565af19"
    },
    {
      "cues": [
        "arrival",
        "backlog",
        "bottleneck",
        "channel",
        "choke",
        "decline",
        "flow",
        "input",
        "lane",
        "narrow",
        "origin",
        "output",
        "passage",
        "path",
        "pipe",
        "queue",
        "resistance",
        "restriction",
        "route",
        "source",
        "supply",
        "throat",
        "throughput",
        "upstream",
        "water"
      ],
      "lesson_text": "ACTION: SEASON. Mechanism label: FLOW. A source sends water through a channel; a narrowed throat adds resistance; downstream output declines while upstream backlog grows. Season FLOW from water_channel_density_01 for Proof 036 level 1.",
      "lineage_hash": "5c7476d4485fe350e96dac3a1f9074a3e56284a991709266a36bfcb1a1368831",
      "lineage_payload": {
        "cues": [
          "backlog",
          "channel",
          "decline",
          "flow",
          "narrow",
          "output",
          "resistance",
          "source",
          "throat",
          "upstream",
          "water"
        ],
        "lesson_text": "ACTION: SEASON. Mechanism label: FLOW. A source sends water through a channel; a narrowed throat adds resistance; downstream output declines while upstream backlog grows. Season FLOW from water_channel_density_01 for Proof 036 level 1.",
        "mechanism": "FLOW",
        "motifs": [
          "Source",
          "Path",
          "Resistance",
          "Flow"
        ],
        "payload_hash": "08136390e9a4e9a56328b88f15cda51a909b048faa1dabbf8d02f0ea01c5ea7f",
        "request_id": "proof-036-level-1-season-001-flow",
        "source_refs": [
          "request",
          "context.summary"
        ]
      },
      "mechanism": "FLOW",
      "motifs": [
        "Source",
        "Path",
        "Resistance",
        "Flow"
      ],
      "record_id": "pond:flow:5c7476d4485fe350"
    },
    {
      "cues": [
        "arrival",
        "backlog",
        "bottleneck",
        "channel",
        "choke",
        "decline",
        "flow",
        "input",
        "lane",
        "narrow",
        "origin",
        "output",
        "passage",
        "path",
        "pipe",
        "queue",
        "resistance",
        "restriction",
        "route",
        "source",
        "supply",
        "throat",
        "throughput",
        "upstream",
        "water"
      ],
      "lesson_text": "ACTION: SEASON. Mechanism label: FLOW. Bins enter a packing path, a metered label step limits passage, and finished kits leave in a trickle. Season FLOW from warehouse_kitting_density_01 for Proof 036 level 1.",
      "lineage_hash": "6e0c931d9629989f62a3820dc1e41d781e625a6a5571ef0ff5c831f67d685341",
      "lineage_payload": {
        "cues": [
          "flow",
          "passage",
          "path"
        ],
        "lesson_text": "ACTION: SEASON. Mechanism label: FLOW. Bins enter a packing path, a metered label step limits passage, and finished kits leave in a trickle. Season FLOW from warehouse_kitting_density_01 for Proof 036 level 1.",
        "mechanism": "FLOW",
        "motifs": [
          "Source",
          "Path",
          "Resistance",
          "Flow"
        ],
        "payload_hash": "3bdc3577231f901b59bcec4b85ecf0bb391c53210594c3f343c10caebcb8d8ae",
        "request_id": "proof-036-level-1-season-004-flow",
        "source_refs": [
          "request",
          "context.summary"
        ]
      },
      "mechanism": "FLOW",
      "motifs": [
        "Source",
        "Path",
        "Resistance",
        "Flow"
      ],
      "record_id": "pond:flow:6e0c931d9629989f"
    },
    {
      "cues": [
        "arrival",
        "backlog",
        "bottleneck",
        "channel",
        "choke",
        "decline",
        "flow",
        "input",
        "lane",
        "narrow",
        "origin",
        "output",
        "passage",
        "path",
        "pipe",
        "queue",
        "resistance",
        "restriction",
        "route",
        "source",
        "supply",
        "throat",
        "throughput",
        "upstream",
        "water"
      ],
      "lesson_text": "ACTION: SEASON. Mechanism label: FLOW. Orders originate in a kitchen, use a runner route, and reach tables late when checkout becomes the choke point. Season FLOW from meal_delivery_density_01 for Proof 036 level 1.",
      "lineage_hash": "7fb47cd80cd9075577d319bf57327b3aafd26acc16dd6f13495722014158f4d8",
      "lineage_payload": {
        "cues": [
          "choke",
          "flow",
          "route"
        ],
        "lesson_text": "ACTION: SEASON. Mechanism label: FLOW. Orders originate in a kitchen, use a runner route, and reach tables late when checkout becomes the choke point. Season FLOW from meal_delivery_density_01 for Proof 036 level 1.",
        "mechanism": "FLOW",
        "motifs": [
          "Source",
          "Path",
          "Resistance",
          "Flow"
        ],
        "payload_hash": "b35d4f91d7596c95a063b6b6d2b2efa47dce324652f97fa64d85a9530fa68db5",
        "request_id": "proof-036-level-1-season-012-flow",
        "source_refs": [
          "request",
          "context.summary"
        ]
      },
      "mechanism": "FLOW",
      "motifs": [
        "Source",
        "Path",
        "Resistance",
        "Flow"
      ],
      "record_id": "pond:flow:7fb47cd80cd90755"
    },
    {
      "cues": [
        "arrival",
        "backlog",
        "bottleneck",
        "channel",
        "choke",
        "decline",
        "flow",
        "input",
        "lane",
        "narrow",
        "origin",
        "output",
        "passage",
        "path",
        "pipe",
        "queue",
        "resistance",
        "restriction",
        "route",
        "source",
        "supply",
        "throat",
        "throughput",
        "upstream",
        "water"
      ],
      "lesson_text": "ACTION: SEASON. Mechanism label: FLOW. Travelers gather at a gate, enter a boarding lane, and seats fill slowly when a document pinch restricts passage. Season FLOW from airport_boarding_density_01 for Proof 036 level 1.",
      "lineage_hash": "88706954decce435ae83532c5c761a3132f55c44944e6536bbbebd156b93692a",
      "lineage_payload": {
        "cues": [
          "flow",
          "lane",
          "passage"
        ],
        "lesson_text": "ACTION: SEASON. Mechanism label: FLOW. Travelers gather at a gate, enter a boarding lane, and seats fill slowly when a document pinch restricts passage. Season FLOW from airport_boarding_density_01 for Proof 036 level 1.",
        "mechanism": "FLOW",
        "motifs": [
          "Source",
          "Path",
          "Resistance",
          "Flow"
        ],
        "payload_hash": "93d6b2d1bdf146e0dc61e4ae06f99bdb1efe5fa9b6c9a2c5536d219340ccf813",
        "request_id": "proof-036-level-1-season-008-flow",
        "source_refs": [
          "request",
          "context.summary"
        ]
      },
      "mechanism": "FLOW",
      "motifs": [
        "Source",
        "Path",
        "Resistance",
        "Flow"
      ],
      "record_id": "pond:flow:88706954decce435"
    },
    {
      "cues": [
        "arrival",
        "backlog",
        "bottleneck",
        "channel",
        "choke",
        "decline",
        "flow",
        "input",
        "lane",
        "narrow",
        "origin",
        "output",
        "passage",
        "path",
        "pipe",
        "queue",
        "resistance",
        "restriction",
        "route",
        "source",
        "supply",
        "throat",
        "throughput",
        "upstream",
        "water"
      ],
      "lesson_text": "ACTION: SEASON. Mechanism label: FLOW. Parcels enter from docks, use one sort aisle, and leave irregularly when a chute meters passage. Season FLOW from delivery_sort_density_01 for Proof 036 level 1.",
      "lineage_hash": "becd4b57960ffe25cc4f886e2f96ce3f88a2b93776f07bbcf00a0d0d4de5a31d",
      "lineage_payload": {
        "cues": [
          "flow",
          "passage"
        ],
        "lesson_text": "ACTION: SEASON. Mechanism label: FLOW. Parcels enter from docks, use one sort aisle, and leave irregularly when a chute meters passage. Season FLOW from delivery_sort_density_01 for Proof 036 level 1.",
        "mechanism": "FLOW",
        "motifs": [
          "Source",
          "Path",
          "Resistance",
          "Flow"
        ],
        "payload_hash": "da9d9b81dbdc08ff53351e7e5ac9a8ae236e434a579aeadba2f2ad5ff0026469",
        "request_id": "proof-036-level-1-season-009-flow",
        "source_refs": [
          "request",
          "context.summary"
        ]
      },
      "mechanism": "FLOW",
      "motifs": [
        "Source",
        "Path",
        "Resistance",
        "Flow"
      ],
      "record_id": "pond:flow:becd4b57960ffe25"
    },
    {
      "cues": [
        "arrival",
        "backlog",
        "bottleneck",
        "channel",
        "choke",
        "decline",
        "flow",
        "input",
        "lane",
        "narrow",
        "origin",
        "output",
        "passage",
        "path",
        "pipe",
        "queue",
        "resistance",
        "restriction",
        "route",
        "source",
        "supply",
        "throat",
        "throughput",
        "upstream",
        "water"
      ],
      "lesson_text": "ACTION: SEASON. Mechanism label: FLOW. Tickets originate from users, pass through a routing board, and reach agents sparsely when approval constrains passage. Season FLOW from support_tickets_density_01 for Proof 036 level 1.",
      "lineage_hash": "c96d239322d5b1afa13ea406589897491fb49e77fd479c9393d33a45427e776d",
      "lineage_payload": {
        "cues": [
          "flow",
          "passage"
        ],
        "lesson_text": "ACTION: SEASON. Mechanism label: FLOW. Tickets originate from users, pass through a routing board, and reach agents sparsely when approval constrains passage. Season FLOW from support_tickets_density_01 for Proof 036 level 1.",
        "mechanism": "FLOW",
        "motifs": [
          "Source",
          "Path",
          "Resistance",
          "Flow"
        ],
        "payload_hash": "df2115b8f4c78e06ff6c4a4532b980ee8cdf1622c6c2735d9329523c6b5ee5ee",
        "request_id": "proof-036-level-1-season-011-flow",
        "source_refs": [
          "request",
          "context.summary"
        ]
      },
      "mechanism": "FLOW",
      "motifs": [
        "Source",
        "Path",
        "Resistance",
        "Flow"
      ],
      "record_id": "pond:flow:c96d239322d5b1af"
    },
    {
      "cues": [
        "arrival",
        "backlog",
        "bottleneck",
        "channel",
        "choke",
        "decline",
        "flow",
        "input",
        "lane",
        "narrow",
        "origin",
        "output",
        "passage",
        "path",
        "pipe",
        "queue",
        "resistance",
        "restriction",
        "route",
        "source",
        "supply",
        "throat",
        "throughput",
        "upstream",
        "water"
      ],
      "lesson_text": "ACTION: SEASON. Mechanism label: FLOW. Events originate at producers, enter a broker route, meet a throttled consumer, and pile before downstream handling. Season FLOW from message_queue_density_01 for Proof 036 level 1.",
      "lineage_hash": "fe5052dd9d44a96bd1d15e74cb94301a6c8562896a6ec48b2147704a69af34f3",
      "lineage_payload": {
        "cues": [
          "flow",
          "route"
        ],
        "lesson_text": "ACTION: SEASON. Mechanism label: FLOW. Events originate at producers, enter a broker route, meet a throttled consumer, and pile before downstream handling. Season FLOW from message_queue_density_01 for Proof 036 level 1.",
        "mechanism": "FLOW",
        "motifs": [
          "Source",
          "Path",
          "Resistance",
          "Flow"
        ],
        "payload_hash": "18e279517d89c87918d8317ea4e271348e7bc4871c03ea8a6e60f7d8412d89bc",
        "request_id": "proof-036-level-1-season-003-flow",
        "source_refs": [
          "request",
          "context.summary"
        ]
      },
      "mechanism": "FLOW",
      "motifs": [
        "Source",
        "Path",
        "Resistance",
        "Flow"
      ],
      "record_id": "pond:flow:fe5052dd9d44a96b"
    },
    {
      "cues": [
        "anchor",
        "bend",
        "bracket",
        "burden",
        "concentration",
        "crack",
        "distribution",
        "failure",
        "load",
        "localized",
        "lug",
        "mass",
        "structure",
        "support",
        "transfer"
      ],
      "lesson_text": "ACTION: SEASON. Mechanism label: LOAD_TRANSFER. Sample mass hangs from pegs; the backboard spreads demand until one peg point takes most and the board splits. Season LOAD_TRANSFER from display_fixture_density_01 for Proof 036 level 1.",
      "lineage_hash": "2425e11cd3666107d311da69cb29463140104cf9082ab29b0084983a328acca0",
      "lineage_payload": {
        "cues": [
          "mass"
        ],
        "lesson_text": "ACTION: SEASON. Mechanism label: LOAD_TRANSFER. Sample mass hangs from pegs; the backboard spreads demand until one peg point takes most and the board splits. Season LOAD_TRANSFER from display_fixture_density_01 for Proof 036 level 1.",
        "mechanism": "LOAD_TRANSFER",
        "motifs": [
          "Load",
          "Distribution",
          "Concentration",
          "Failure"
        ],
        "payload_hash": "9bc1f414c00773889676cf095ece4af369ea66915ba75fe1ca9229c837a46a2e",
        "request_id": "proof-036-level-1-season-036-load_transfer",
        "source_refs": [
          "request",
          "context.summary"
        ]
      },
      "mechanism": "LOAD_TRANSFER",
      "motifs": [
        "Load",
        "Distribution",
        "Concentration",
        "Failure"
      ],
      "record_id": "pond:load_transfer:2425e11cd3666107"
    },
    {
      "cues": [
        "anchor",
        "bend",
        "bracket",
        "burden",
        "concentration",
        "crack",
        "distribution",
        "failure",
        "load",
        "localized",
        "lug",
        "mass",
        "structure",
        "support",
        "transfer"
      ],
      "lesson_text": "ACTION: SEASON. Mechanism label: LOAD_TRANSFER. Wet fabric adds burden; the frame spreads demand until a front lug is singled out and the corner sags. Season LOAD_TRANSFER from awning_frame_density_01 for Proof 036 level 1.",
      "lineage_hash": "30472e8739faa106d34d5e57efbdb9401c927b6961d7d97926bc23629ddb8b6e",
      "lineage_payload": {
        "cues": [
          "burden",
          "lug"
        ],
        "lesson_text": "ACTION: SEASON. Mechanism label: LOAD_TRANSFER. Wet fabric adds burden; the frame spreads demand until a front lug is singled out and the corner sags. Season LOAD_TRANSFER from awning_frame_density_01 for Proof 036 level 1.",
        "mechanism": "LOAD_TRANSFER",
        "motifs": [
          "Load",
          "Distribution",
          "Concentration",
          "Failure"
        ],
        "payload_hash": "03fe9d15017f885df7afdbab640201c18580252f24ac69515eb10510a317a604",
        "request_id": "proof-036-level-1-season-033-load_transfer",
        "source_refs": [
          "request",
          "context.summary"
        ]
      },
      "mechanism": "LOAD_TRANSFER",
      "motifs": [
        "Load",
        "Distribution",
        "Concentration",
        "Failure"
      ],
      "record_id": "pond:load_transfer:30472e8739faa106"
    },
    {
      "cues": [
        "anchor",
        "bend",
        "bracket",
        "burden",
        "concentration",
        "crack",
        "distribution",
        "failure",
        "load",
        "localized",
        "lug",
        "mass",
        "structure",
        "support",
        "transfer"
      ],
      "lesson_text": "ACTION: SEASON. Mechanism label: LOAD_TRANSFER. Glassware mass rests on a tray; side rails share demand until one rail takes most and the tray bows. Season LOAD_TRANSFER from lab_shelf_density_01 for Proof 036 level 1.",
      "lineage_hash": "31f492078c5cd46329491a60d3bb3493ac61762bd74a4a0ee66055e9e607deec",
      "lineage_payload": {
        "cues": [
          "mass"
        ],
        "lesson_text": "ACTION: SEASON. Mechanism label: LOAD_TRANSFER. Glassware mass rests on a tray; side rails share demand until one rail takes most and the tray bows. Season LOAD_TRANSFER from lab_shelf_density_01 for Proof 036 level 1.",
        "mechanism": "LOAD_TRANSFER",
        "motifs": [
          "Load",
          "Distribution",
          "Concentration",
          "Failure"
        ],
        "payload_hash": "3d7d13c04ab9d9e35e57c8b3ad9f5149bc08d8665b5b82dfa3b8c536479e51f2",
        "request_id": "proof-036-level-1-season-034-load_transfer",
        "source_refs": [
          "request",
          "context.summary"
        ]
      },
      "mechanism": "LOAD_TRANSFER",
      "motifs": [
        "Load",
        "Distribution",
        "Concentration",
        "Failure"
      ],
      "record_id": "pond:load_transfer:31f492078c5cd463"
    },
    {
      "cues": [
        "anchor",
        "bend",
        "bracket",
        "burden",
        "concentration",
        "crack",
        "distribution",
        "failure",
        "load",
        "localized",
        "lug",
        "mass",
        "structure",
        "support",
        "transfer"
      ],
      "lesson_text": "ACTION: SEASON. Mechanism label: LOAD_TRANSFER. A panel imposes burden on a frame; rails should share demand, but one lug receives most and the frame creases. Season LOAD_TRANSFER from gallery_hanging_density_01 for Proof 036 level 1.",
      "lineage_hash": "3366f03661f9046140d13006d687c2769f7cf0ca36fcfb5f9a431e63982af2f6",
      "lineage_payload": {
        "cues": [
          "burden",
          "lug"
        ],
        "lesson_text": "ACTION: SEASON. Mechanism label: LOAD_TRANSFER. A panel imposes burden on a frame; rails should share demand, but one lug receives most and the frame creases. Season LOAD_TRANSFER from gallery_hanging_density_01 for Proof 036 level 1.",
        "mechanism": "LOAD_TRANSFER",
        "motifs": [
          "Load",
          "Distribution",
          "Concentration",
          "Failure"
        ],
        "payload_hash": "e75c3417efbf99b097546b0f8c2f060672aa104d9e89231c6c0682ba79b1e915",
        "request_id": "proof-036-level-1-season-025-load_transfer",
        "source_refs": [
          "request",
          "context.summary"
        ]
      },
      "mechanism": "LOAD_TRANSFER",
      "motifs": [
        "Load",
        "Distribution",
        "Concentration",
        "Failure"
      ],
      "record_id": "pond:load_transfer:3366f03661f90461"
    },
    {
      "cues": [
        "anchor",
        "bend",
        "bracket",
        "burden",
        "concentration",
        "crack",
        "distribution",
        "failure",
        "load",
        "localized",
        "lug",
        "mass",
        "structure",
        "support",
        "transfer"
      ],
      "lesson_text": "ACTION: SEASON. Mechanism label: LOAD_TRANSFER. Wind pushes a panel; frame bars distribute demand until one fastener lug takes most and wrinkles spread. Season LOAD_TRANSFER from sign_frame_density_01 for Proof 036 level 1.",
      "lineage_hash": "6ffafea26c11e9112a3266527b4d5ad3414e67f343074f91e36756dbcefddf58",
      "lineage_payload": {
        "cues": [
          "lug"
        ],
        "lesson_text": "ACTION: SEASON. Mechanism label: LOAD_TRANSFER. Wind pushes a panel; frame bars distribute demand until one fastener lug takes most and wrinkles spread. Season LOAD_TRANSFER from sign_frame_density_01 for Proof 036 level 1.",
        "mechanism": "LOAD_TRANSFER",
        "motifs": [
          "Load",
          "Distribution",
          "Concentration",
          "Failure"
        ],
        "payload_hash": "084505d00ad15cd875b9964fd3bb1f377ce9183c9e872b921cdd375c9d33e23a",
        "request_id": "proof-036-level-1-season-029-load_transfer",
        "source_refs": [
          "request",
          "context.summary"
        ]
      },
      "mechanism": "LOAD_TRANSFER",
      "motifs": [
        "Load",
        "Distribution",
        "Concentration",
        "Failure"
      ],
      "record_id": "pond:load_transfer:6ffafea26c11e911"
    },
    {
      "cues": [
        "anchor",
        "bend",
        "bracket",
        "burden",
        "concentration",
        "crack",
        "distribution",
        "failure",
        "load",
        "localized",
        "lug",
        "mass",
        "structure",
        "support",
        "transfer"
      ],
      "lesson_text": "ACTION: SEASON. Mechanism label: LOAD_TRANSFER. Equipment mass sits on shelf rails; one rear lug takes excess demand and the rack face cants. Season LOAD_TRANSFER from server_rack_density_01 for Proof 036 level 1.",
      "lineage_hash": "7bc147a684f2e73d9870105e6373c030db1d3e190475d67af2e538fc201002e1",
      "lineage_payload": {
        "cues": [
          "lug",
          "mass"
        ],
        "lesson_text": "ACTION: SEASON. Mechanism label: LOAD_TRANSFER. Equipment mass sits on shelf rails; one rear lug takes excess demand and the rack face cants. Season LOAD_TRANSFER from server_rack_density_01 for Proof 036 level 1.",
        "mechanism": "LOAD_TRANSFER",
        "motifs": [
          "Load",
          "Distribution",
          "Concentration",
          "Failure"
        ],
        "payload_hash": "94f5a6d69c5b8f2e617b7af98b153402d0f66298d8a6f50f4d2b92d65e9b8ca1",
        "request_id": "proof-036-level-1-season-027-load_transfer",
        "source_refs": [
          "request",
          "context.summary"
        ]
      },
      "mechanism": "LOAD_TRANSFER",
      "motifs": [
        "Load",
        "Distribution",
        "Concentration",
        "Failure"
      ],
      "record_id": "pond:load_transfer:7bc147a684f2e73d"
    },
    {
      "cues": [
        "anchor",
        "bend",
        "bracket",
        "burden",
        "concentration",
        "crack",
        "distribution",
        "failure",
        "load",
        "localized",
        "lug",
        "mass",
        "structure",
        "support",
        "transfer"
      ],
      "lesson_text": "ACTION: SEASON. Mechanism label: LOAD_TRANSFER. Speaker mass sits on a platform; one cross rib takes most burden and the surface creases. Season LOAD_TRANSFER from portable_stage_density_01 for Proof 036 level 1.",
      "lineage_hash": "83948cea4874489ade787a2620e0e4c7923eb6ea056ab64869ba2d36b46b14fc",
      "lineage_payload": {
        "cues": [
          "burden",
          "mass"
        ],
        "lesson_text": "ACTION: SEASON. Mechanism label: LOAD_TRANSFER. Speaker mass sits on a platform; one cross rib takes most burden and the surface creases. Season LOAD_TRANSFER from portable_stage_density_01 for Proof 036 level 1.",
        "mechanism": "LOAD_TRANSFER",
        "motifs": [
          "Load",
          "Distribution",
          "Concentration",
          "Failure"
        ],
        "payload_hash": "c76b2e3a56dd8b755b2ae42013b03d5e0b03129e730b84f984d131f592862fc1",
        "request_id": "proof-036-level-1-season-032-load_transfer",
        "source_refs": [
          "request",
          "context.summary"
        ]
      },
      "mechanism": "LOAD_TRANSFER",
      "motifs": [
        "Load",
        "Distribution",
        "Concentration",
        "Failure"
      ],
      "record_id": "pond:load_transfer:83948cea4874489a"
    },
    {
      "cues": [
        "anchor",
        "bend",
        "bracket",
        "burden",
        "concentration",
        "crack",
        "distribution",
        "failure",
        "load",
        "localized",
        "lug",
        "mass",
        "structure",
        "support",
        "transfer"
      ],
      "lesson_text": "ACTION: SEASON. Mechanism label: LOAD_TRANSFER. Bikes impose burden; rack arms share demand until one weld lug takes excess and the arm bends. Season LOAD_TRANSFER from bike_rack_density_01 for Proof 036 level 1.",
      "lineage_hash": "8856422358e58bb4b69f68b03fe59155448d2565b1ad857ff1d8c1c10e34a943",
      "lineage_payload": {
        "cues": [
          "bend",
          "burden",
          "lug"
        ],
        "lesson_text": "ACTION: SEASON. Mechanism label: LOAD_TRANSFER. Bikes impose burden; rack arms share demand until one weld lug takes excess and the arm bends. Season LOAD_TRANSFER from bike_rack_density_01 for Proof 036 level 1.",
        "mechanism": "LOAD_TRANSFER",
        "motifs": [
          "Load",
          "Distribution",
          "Concentration",
          "Failure"
        ],
        "payload_hash": "768ee0a337242e85cca2cf0e31719a324941a1390557c916cedf79fb93b5cc33",
        "request_id": "proof-036-level-1-season-035-load_transfer",
        "source_refs": [
          "request",
          "context.summary"
        ]
      },
      "mechanism": "LOAD_TRANSFER",
      "motifs": [
        "Load",
        "Distribution",
        "Concentration",
        "Failure"
      ],
      "record_id": "pond:load_transfer:8856422358e58bb4"
    },
    {
      "cues": [
        "anchor",
        "bend",
        "bracket",
        "burden",
        "concentration",
        "crack",
        "distribution",
        "failure",
        "load",
        "localized",
        "lug",
        "mass",
        "structure",
        "support",
        "transfer"
      ],
      "lesson_text": "ACTION: SEASON. Mechanism label: LOAD_TRANSFER. Performers add burden to deck panels; ribs distribute it until one rib takes local demand and the deck warps. Season LOAD_TRANSFER from stage_platform_density_01 for Proof 036 level 1.",
      "lineage_hash": "895ff9d17e49f69b152bc005f7730fbc0c637080d68f1ca90aaa13f2ea3f6284",
      "lineage_payload": {
        "cues": [
          "burden"
        ],
        "lesson_text": "ACTION: SEASON. Mechanism label: LOAD_TRANSFER. Performers add burden to deck panels; ribs distribute it until one rib takes local demand and the deck warps. Season LOAD_TRANSFER from stage_platform_density_01 for Proof 036 level 1.",
        "mechanism": "LOAD_TRANSFER",
        "motifs": [
          "Load",
          "Distribution",
          "Concentration",
          "Failure"
        ],
        "payload_hash": "fd62950c18266ce73f3a09d355a131fd6f63b55501b0fbcd19415cf7f58ac63f",
        "request_id": "proof-036-level-1-season-026-load_transfer",
        "source_refs": [
          "request",
          "context.summary"
        ]
      },
      "mechanism": "LOAD_TRANSFER",
      "motifs": [
        "Load",
        "Distribution",
        "Concentration",
        "Failure"
      ],
      "record_id": "pond:load_transfer:895ff9d17e49f69b"
    },
    {
      "cues": [
        "anchor",
        "bend",
        "bracket",
        "burden",
        "concentration",
        "crack",
        "distribution",
        "failure",
        "load",
        "localized",
        "lug",
        "mass",
        "structure",
        "support",
        "transfer"
      ],
      "lesson_text": "ACTION: SEASON. Mechanism label: LOAD_TRANSFER. Plant trays add mass to bench slats; one slat receives local demand and the tray line dips. Season LOAD_TRANSFER from greenhouse_bench_density_01 for Proof 036 level 1.",
      "lineage_hash": "ad55ee21cd6092aee32d13aef923e121dfdbe46bc74f87965c72b33b938691bd",
      "lineage_payload": {
        "cues": [
          "mass"
        ],
        "lesson_text": "ACTION: SEASON. Mechanism label: LOAD_TRANSFER. Plant trays add mass to bench slats; one slat receives local demand and the tray line dips. Season LOAD_TRANSFER from greenhouse_bench_density_01 for Proof 036 level 1.",
        "mechanism": "LOAD_TRANSFER",
        "motifs": [
          "Load",
          "Distribution",
          "Concentration",
          "Failure"
        ],
        "payload_hash": "8938e9b20e8d7ac8e202f4f94018e3175d0c54488912b67c44c2e80e0926b47a",
        "request_id": "proof-036-level-1-season-028-load_transfer",
        "source_refs": [
          "request",
          "context.summary"
        ]
      },
      "mechanism": "LOAD_TRANSFER",
      "motifs": [
        "Load",
        "Distribution",
        "Concentration",
        "Failure"
      ],
      "record_id": "pond:load_transfer:ad55ee21cd6092ae"
    },
    {
      "cues": [
        "anchor",
        "bend",
        "bracket",
        "burden",
        "concentration",
        "crack",
        "distribution",
        "failure",
        "load",
        "localized",
        "lug",
        "mass",
        "structure",
        "support",
        "transfer"
      ],
      "lesson_text": "ACTION: SEASON. Mechanism label: LOAD_TRANSFER. Hull mass rests across pads; one pad takes point demand and the hull skin dents. Season LOAD_TRANSFER from boat_rack_density_01 for Proof 036 level 1.",
      "lineage_hash": "d82fa9b29027d8fff05efcdbf5d8108675be2fa18ab5c4f336a3a4ce860800c1",
      "lineage_payload": {
        "cues": [
          "mass"
        ],
        "lesson_text": "ACTION: SEASON. Mechanism label: LOAD_TRANSFER. Hull mass rests across pads; one pad takes point demand and the hull skin dents. Season LOAD_TRANSFER from boat_rack_density_01 for Proof 036 level 1.",
        "mechanism": "LOAD_TRANSFER",
        "motifs": [
          "Load",
          "Distribution",
          "Concentration",
          "Failure"
        ],
        "payload_hash": "4cca227e0fcb54947aae7f8b60c7d63b227b8b8d513c84112ebf46de9dfd8d53",
        "request_id": "proof-036-level-1-season-030-load_transfer",
        "source_refs": [
          "request",
          "context.summary"
        ]
      },
      "mechanism": "LOAD_TRANSFER",
      "motifs": [
        "Load",
        "Distribution",
        "Concentration",
        "Failure"
      ],
      "record_id": "pond:load_transfer:d82fa9b29027d8ff"
    },
    {
      "cues": [
        "anchor",
        "bend",
        "bracket",
        "burden",
        "concentration",
        "crack",
        "distribution",
        "failure",
        "load",
        "localized",
        "lug",
        "mass",
        "structure",
        "support",
        "transfer"
      ],
      "lesson_text": "ACTION: SEASON. Mechanism label: LOAD_TRANSFER. Array mass sits across rails; one clamp lug takes excess demand and the edge drops. Season LOAD_TRANSFER from solar_array_density_01 for Proof 036 level 1.",
      "lineage_hash": "e5180bdd77814785f30fcfd983d266cf28b18a6b59f95788b9668f8991698e79",
      "lineage_payload": {
        "cues": [
          "lug",
          "mass"
        ],
        "lesson_text": "ACTION: SEASON. Mechanism label: LOAD_TRANSFER. Array mass sits across rails; one clamp lug takes excess demand and the edge drops. Season LOAD_TRANSFER from solar_array_density_01 for Proof 036 level 1.",
        "mechanism": "LOAD_TRANSFER",
        "motifs": [
          "Load",
          "Distribution",
          "Concentration",
          "Failure"
        ],
        "payload_hash": "4024c39ea73b2a4e7590eb06b8fe4f436e68cd375650b2433ccc5f45709835d5",
        "request_id": "proof-036-level-1-season-031-load_transfer",
        "source_refs": [
          "request",
          "context.summary"
        ]
      },
      "mechanism": "LOAD_TRANSFER",
      "motifs": [
        "Load",
        "Distribution",
        "Concentration",
        "Failure"
      ],
      "record_id": "pond:load_transfer:e5180bdd77814785"
    },
    {
      "cues": [
        "bearing",
        "drag",
        "friction",
        "journal",
        "lock",
        "pivot",
        "rotate",
        "rotating",
        "rotation",
        "rough",
        "seize",
        "seizure",
        "socket",
        "support",
        "turn",
        "wobble"
      ],
      "lesson_text": "ACTION: SEASON. Mechanism label: SUPPORTED_ROTATION. A ring pivots on a yoke; grit at the pivot adds drag and makes the sweep jerky. Season SUPPORTED_ROTATION from camera_gimbal_density_01 for Proof 036 level 1.",
      "lineage_hash": "2fbb2d0b511f344d5df15aa645cfe5f4d6ce1e00a2e12e744e27c399d40a46b0",
      "lineage_payload": {
        "cues": [
          "drag",
          "pivot"
        ],
        "lesson_text": "ACTION: SEASON. Mechanism label: SUPPORTED_ROTATION. A ring pivots on a yoke; grit at the pivot adds drag and makes the sweep jerky. Season SUPPORTED_ROTATION from camera_gimbal_density_01 for Proof 036 level 1.",
        "mechanism": "SUPPORTED_ROTATION",
        "motifs": [
          "Rotation",
          "Support",
          "Friction",
          "Failure"
        ],
        "payload_hash": "21435f14877b750259038bf8a41763b88b3f25de3a592a6f5f39cec945a6c7bc",
        "request_id": "proof-036-level-1-season-014-supported_rotation",
        "source_refs": [
          "request",
          "context.summary"
        ]
      },
      "mechanism": "SUPPORTED_ROTATION",
      "motifs": [
        "Rotation",
        "Support",
        "Friction",
        "Failure"
      ],
      "record_id": "pond:supported_rotation:2fbb2d0b511f344d"
    },
    {
      "cues": [
        "bearing",
        "drag",
        "friction",
        "journal",
        "lock",
        "pivot",
        "rotate",
        "rotating",
        "rotation",
        "rough",
        "seize",
        "seizure",
        "socket",
        "support",
        "turn",
        "wobble"
      ],
      "lesson_text": "ACTION: SEASON. Mechanism label: SUPPORTED_ROTATION. A rewinder core turns on a hub seat; rough contact warms and roll travel lurches. Season SUPPORTED_ROTATION from label_rewinder_density_01 for Proof 036 level 1.",
      "lineage_hash": "30445ea0e88c38fb7d3c83d9451da2cbf070c2a2e16aa8c05a0fadc24a74e3a3",
      "lineage_payload": {
        "cues": [
          "rough",
          "turn"
        ],
        "lesson_text": "ACTION: SEASON. Mechanism label: SUPPORTED_ROTATION. A rewinder core turns on a hub seat; rough contact warms and roll travel lurches. Season SUPPORTED_ROTATION from label_rewinder_density_01 for Proof 036 level 1.",
        "mechanism": "SUPPORTED_ROTATION",
        "motifs": [
          "Rotation",
          "Support",
          "Friction",
          "Failure"
        ],
        "payload_hash": "396c3148f2c9c833e7fea3a62734bd06eb8e8baa7d625f92833fe57d62eaffa5",
        "request_id": "proof-036-level-1-season-022-supported_rotation",
        "source_refs": [
          "request",
          "context.summary"
        ]
      },
      "mechanism": "SUPPORTED_ROTATION",
      "motifs": [
        "Rotation",
        "Support",
        "Friction",
        "Failure"
      ],
      "record_id": "pond:supported_rotation:30445ea0e88c38fb"
    },
    {
      "cues": [
        "bearing",
        "drag",
        "friction",
        "journal",
        "lock",
        "pivot",
        "rotate",
        "rotating",
        "rotation",
        "rough",
        "seize",
        "seizure",
        "socket",
        "support",
        "turn",
        "wobble"
      ],
      "lesson_text": "ACTION: SEASON. Mechanism label: SUPPORTED_ROTATION. An azimuth plate circles on a base race; dust creates grinding and tracking wobbles. Season SUPPORTED_ROTATION from telescope_mount_density_01 for Proof 036 level 1.",
      "lineage_hash": "4d6cedb54f0e99284fca8c946d0933138680724c83899e012390128b7518060b",
      "lineage_payload": {
        "cues": [
          "wobble"
        ],
        "lesson_text": "ACTION: SEASON. Mechanism label: SUPPORTED_ROTATION. An azimuth plate circles on a base race; dust creates grinding and tracking wobbles. Season SUPPORTED_ROTATION from telescope_mount_density_01 for Proof 036 level 1.",
        "mechanism": "SUPPORTED_ROTATION",
        "motifs": [
          "Rotation",
          "Support",
          "Friction",
          "Failure"
        ],
        "payload_hash": "f6e578ff9ac6bf344deea22643d80da184477a5993f65095972ab9feb35956d2",
        "request_id": "proof-036-level-1-season-021-supported_rotation",
        "source_refs": [
          "request",
          "context.summary"
        ]
      },
      "mechanism": "SUPPORTED_ROTATION",
      "motifs": [
        "Rotation",
        "Support",
        "Friction",
        "Failure"
      ],
      "record_id": "pond:supported_rotation:4d6cedb54f0e9928"
    },
    {
      "cues": [
        "bearing",
        "drag",
        "friction",
        "journal",
        "lock",
        "pivot",
        "rotate",
        "rotating",
        "rotation",
        "rough",
        "seize",
        "seizure",
        "socket",
        "support",
        "turn",
        "wobble"
      ],
      "lesson_text": "ACTION: SEASON. Mechanism label: SUPPORTED_ROTATION. A roller turns under cartons; dry contact in an end cup grinds and cartons hesitate. Season SUPPORTED_ROTATION from conveyor_roller_density_01 for Proof 036 level 1.",
      "lineage_hash": "4dd1aa8ed0fb8e8b8941c6fd67aadce0ce01aa40ca5ff8a2d5faa891578c0490",
      "lineage_payload": {
        "cues": [
          "turn"
        ],
        "lesson_text": "ACTION: SEASON. Mechanism label: SUPPORTED_ROTATION. A roller turns under cartons; dry contact in an end cup grinds and cartons hesitate. Season SUPPORTED_ROTATION from conveyor_roller_density_01 for Proof 036 level 1.",
        "mechanism": "SUPPORTED_ROTATION",
        "motifs": [
          "Rotation",
          "Support",
          "Friction",
          "Failure"
        ],
        "payload_hash": "376adf67ce307b81bef0851b2586f731d343f97c1185401669069c56f630ab98",
        "request_id": "proof-036-level-1-season-015-supported_rotation",
        "source_refs": [
          "request",
          "context.summary"
        ]
      },
      "mechanism": "SUPPORTED_ROTATION",
      "motifs": [
        "Rotation",
        "Support",
        "Friction",
        "Failure"
      ],
      "record_id": "pond:supported_rotation:4dd1aa8ed0fb8e8b"
    },
    {
      "cues": [
        "bearing",
        "drag",
        "friction",
        "journal",
        "lock",
        "pivot",
        "rotate",
        "rotating",
        "rotation",
        "rough",
        "seize",
        "seizure",
        "socket",
        "support",
        "turn",
        "wobble"
      ],
      "lesson_text": "ACTION: SEASON. Mechanism label: SUPPORTED_ROTATION. A disk turns around a center socket; rising friction at the socket makes the turn rough and eventually stuck. Season SUPPORTED_ROTATION from scanner_carousel_density_01 for Proof 036 level 1.",
      "lineage_hash": "6a7dc66b8ff38540f900ae22f837e8ce83e1127cb07cf1ca3e35ef6b20022e2d",
      "lineage_payload": {
        "cues": [
          "friction",
          "rough",
          "socket",
          "turn"
        ],
        "lesson_text": "ACTION: SEASON. Mechanism label: SUPPORTED_ROTATION. A disk turns around a center socket; rising friction at the socket makes the turn rough and eventually stuck. Season SUPPORTED_ROTATION from scanner_carousel_density_01 for Proof 036 level 1.",
        "mechanism": "SUPPORTED_ROTATION",
        "motifs": [
          "Rotation",
          "Support",
          "Friction",
          "Failure"
        ],
        "payload_hash": "9e318410b09213c076c8347d01c5f46f98224f39f0c2dda8ec96715263511042",
        "request_id": "proof-036-level-1-season-013-supported_rotation",
        "source_refs": [
          "request",
          "context.summary"
        ]
      },
      "mechanism": "SUPPORTED_ROTATION",
      "motifs": [
        "Rotation",
        "Support",
        "Friction",
        "Failure"
      ],
      "record_id": "pond:supported_rotation:6a7dc66b8ff38540"
    },
    {
      "cues": [
        "bearing",
        "drag",
        "friction",
        "journal",
        "lock",
        "pivot",
        "rotate",
        "rotating",
        "rotation",
        "rough",
        "seize",
        "seizure",
        "socket",
        "support",
        "turn",
        "wobble"
      ],
      "lesson_text": "ACTION: SEASON. Mechanism label: SUPPORTED_ROTATION. A valve rotor turns against a seat ring; rough contact warms and the valve locks shut. Season SUPPORTED_ROTATION from valve_rotor_density_01 for Proof 036 level 1.",
      "lineage_hash": "9e06a42360b8fb35153955d50664563228d98805906b80fd94fff4ece3036030",
      "lineage_payload": {
        "cues": [
          "lock",
          "rough",
          "turn"
        ],
        "lesson_text": "ACTION: SEASON. Mechanism label: SUPPORTED_ROTATION. A valve rotor turns against a seat ring; rough contact warms and the valve locks shut. Season SUPPORTED_ROTATION from valve_rotor_density_01 for Proof 036 level 1.",
        "mechanism": "SUPPORTED_ROTATION",
        "motifs": [
          "Rotation",
          "Support",
          "Friction",
          "Failure"
        ],
        "payload_hash": "a1f1fb0a50a9caea248eebc51940340c337f75f53e3ae534c69c4b444d040936",
        "request_id": "proof-036-level-1-season-020-supported_rotation",
        "source_refs": [
          "request",
          "context.summary"
        ]
      },
      "mechanism": "SUPPORTED_ROTATION",
      "motifs": [
        "Rotation",
        "Support",
        "Friction",
        "Failure"
      ],
      "record_id": "pond:supported_rotation:9e06a42360b8fb35"
    },
    {
      "cues": [
        "bearing",
        "drag",
        "friction",
        "journal",
        "lock",
        "pivot",
        "rotate",
        "rotating",
        "rotation",
        "rough",
        "seize",
        "seizure",
        "socket",
        "support",
        "turn",
        "wobble"
      ],
      "lesson_text": "ACTION: SEASON. Mechanism label: SUPPORTED_ROTATION. A lamp yoke swivels in side bushings; dry contact squeals and the sweep stalls. Season SUPPORTED_ROTATION from lighting_yoke_density_01 for Proof 036 level 1.",
      "lineage_hash": "9ffceca5bc1e3e83329631a0229af7c6a1a434cd35b16555ee202375e5c9a056",
      "lineage_payload": {
        "cues": [],
        "lesson_text": "ACTION: SEASON. Mechanism label: SUPPORTED_ROTATION. A lamp yoke swivels in side bushings; dry contact squeals and the sweep stalls. Season SUPPORTED_ROTATION from lighting_yoke_density_01 for Proof 036 level 1.",
        "mechanism": "SUPPORTED_ROTATION",
        "motifs": [
          "Rotation",
          "Support",
          "Friction",
          "Failure"
        ],
        "payload_hash": "52f41b9f991c6681259a6e001276e1cb848ce2bfce307f0b82abbdb554f779b7",
        "request_id": "proof-036-level-1-season-024-supported_rotation",
        "source_refs": [
          "request",
          "context.summary"
        ]
      },
      "mechanism": "SUPPORTED_ROTATION",
      "motifs": [
        "Rotation",
        "Support",
        "Friction",
        "Failure"
      ],
      "record_id": "pond:supported_rotation:9ffceca5bc1e3e83"
    },
    {
      "cues": [
        "bearing",
        "drag",
        "friction",
        "journal",
        "lock",
        "pivot",
        "rotate",
        "rotating",
        "rotation",
        "rough",
        "seize",
        "seizure",
        "socket",
        "support",
        "turn",
        "wobble"
      ],
      "lesson_text": "ACTION: SEASON. Mechanism label: SUPPORTED_ROTATION. A turnstile arm rotates around a center journal; rough contact vibrates and the arm stops mid-cycle. Season SUPPORTED_ROTATION from ticket_turnstile_density_01 for Proof 036 level 1.",
      "lineage_hash": "b12ebc79bf22ec0157747af9527e2ed154ec0d3cd6709263bd05c5783cf3c331",
      "lineage_payload": {
        "cues": [
          "journal",
          "rotate",
          "rough"
        ],
        "lesson_text": "ACTION: SEASON. Mechanism label: SUPPORTED_ROTATION. A turnstile arm rotates around a center journal; rough contact vibrates and the arm stops mid-cycle. Season SUPPORTED_ROTATION from ticket_turnstile_density_01 for Proof 036 level 1.",
        "mechanism": "SUPPORTED_ROTATION",
        "motifs": [
          "Rotation",
          "Support",
          "Friction",
          "Failure"
        ],
        "payload_hash": "1500099f81282d1712dadf6d5924e51618b63a43c323e2becc8d8c12a654f81b",
        "request_id": "proof-036-level-1-season-018-supported_rotation",
        "source_refs": [
          "request",
          "context.summary"
        ]
      },
      "mechanism": "SUPPORTED_ROTATION",
      "motifs": [
        "Rotation",
        "Support",
        "Friction",
        "Failure"
      ],
      "record_id": "pond:supported_rotation:b12ebc79bf22ec01"
    },
    {
      "cues": [
        "bearing",
        "drag",
        "friction",
        "journal",
        "lock",
        "pivot",
        "rotate",
        "rotating",
        "rotation",
        "rough",
        "seize",
        "seizure",
        "socket",
        "support",
        "turn",
        "wobble"
      ],
      "lesson_text": "ACTION: SEASON. Mechanism label: SUPPORTED_ROTATION. A joint ring turns in a cup; abrasive dust increases drag and the arm hesitates. Season SUPPORTED_ROTATION from robot_joint_density_01 for Proof 036 level 1.",
      "lineage_hash": "ea7db240180ec734bcb8569f0c9e8b4934737e23382332a63713738b745f7e56",
      "lineage_payload": {
        "cues": [
          "drag",
          "turn"
        ],
        "lesson_text": "ACTION: SEASON. Mechanism label: SUPPORTED_ROTATION. A joint ring turns in a cup; abrasive dust increases drag and the arm hesitates. Season SUPPORTED_ROTATION from robot_joint_density_01 for Proof 036 level 1.",
        "mechanism": "SUPPORTED_ROTATION",
        "motifs": [
          "Rotation",
          "Support",
          "Friction",
          "Failure"
        ],
        "payload_hash": "44e9d794317dd1d4c0568c5542408ad8f20b186948e73f34eba15c23ce8a9903",
        "request_id": "proof-036-level-1-season-019-supported_rotation",
        "source_refs": [
          "request",
          "context.summary"
        ]
      },
      "mechanism": "SUPPORTED_ROTATION",
      "motifs": [
        "Rotation",
        "Support",
        "Friction",
        "Failure"
      ],
      "record_id": "pond:supported_rotation:ea7db240180ec734"
    },
    {
      "cues": [
        "bearing",
        "drag",
        "friction",
        "journal",
        "lock",
        "pivot",
        "rotate",
        "rotating",
        "rotation",
        "rough",
        "seize",
        "seizure",
        "socket",
        "support",
        "turn",
        "wobble"
      ],
      "lesson_text": "ACTION: SEASON. Mechanism label: SUPPORTED_ROTATION. A selector ring revolves in a small socket; abrasion grows and the dial sticks between settings. Season SUPPORTED_ROTATION from dial_selector_density_01 for Proof 036 level 1.",
      "lineage_hash": "f0b64c00b11d6a1f6f410a4d56561008cb32ce181ff11182409405d2eea90a12",
      "lineage_payload": {
        "cues": [
          "socket"
        ],
        "lesson_text": "ACTION: SEASON. Mechanism label: SUPPORTED_ROTATION. A selector ring revolves in a small socket; abrasion grows and the dial sticks between settings. Season SUPPORTED_ROTATION from dial_selector_density_01 for Proof 036 level 1.",
        "mechanism": "SUPPORTED_ROTATION",
        "motifs": [
          "Rotation",
          "Support",
          "Friction",
          "Failure"
        ],
        "payload_hash": "cb198c194f4996c1d7068c98474f5981c238021f7baf9ffbdfc305b2e51900cf",
        "request_id": "proof-036-level-1-season-016-supported_rotation",
        "source_refs": [
          "request",
          "context.summary"
        ]
      },
      "mechanism": "SUPPORTED_ROTATION",
      "motifs": [
        "Rotation",
        "Support",
        "Friction",
        "Failure"
      ],
      "record_id": "pond:supported_rotation:f0b64c00b11d6a1f"
    },
    {
      "cues": [
        "bearing",
        "drag",
        "friction",
        "journal",
        "lock",
        "pivot",
        "rotate",
        "rotating",
        "rotation",
        "rough",
        "seize",
        "seizure",
        "socket",
        "support",
        "turn",
        "wobble"
      ],
      "lesson_text": "ACTION: SEASON. Mechanism label: SUPPORTED_ROTATION. A pointer spindle turns in a tiny jewel seat; grit adds drag and the pointer freezes. Season SUPPORTED_ROTATION from meter_pointer_density_01 for Proof 036 level 1.",
      "lineage_hash": "f8556fa21fb6efbc7be9765d921efc8e331fec806898cc923100267639e156db",
      "lineage_payload": {
        "cues": [
          "drag",
          "turn"
        ],
        "lesson_text": "ACTION: SEASON. Mechanism label: SUPPORTED_ROTATION. A pointer spindle turns in a tiny jewel seat; grit adds drag and the pointer freezes. Season SUPPORTED_ROTATION from meter_pointer_density_01 for Proof 036 level 1.",
        "mechanism": "SUPPORTED_ROTATION",
        "motifs": [
          "Rotation",
          "Support",
          "Friction",
          "Failure"
        ],
        "payload_hash": "9d5533233ef31a7927d4491fd7500658a8b4e712d354ac5fb6ac9021ec7adcb3",
        "request_id": "proof-036-level-1-season-023-supported_rotation",
        "source_refs": [
          "request",
          "context.summary"
        ]
      },
      "mechanism": "SUPPORTED_ROTATION",
      "motifs": [
        "Rotation",
        "Support",
        "Friction",
        "Failure"
      ],
      "record_id": "pond:supported_rotation:f8556fa21fb6efbc"
    },
    {
      "cues": [
        "bearing",
        "drag",
        "friction",
        "journal",
        "lock",
        "pivot",
        "rotate",
        "rotating",
        "rotation",
        "rough",
        "seize",
        "seizure",
        "socket",
        "support",
        "turn",
        "wobble"
      ],
      "lesson_text": "ACTION: SEASON. Mechanism label: SUPPORTED_ROTATION. A stage wheel circles on a journal seat; drag rises and fine adjustment locks. Season SUPPORTED_ROTATION from microscope_stage_density_01 for Proof 036 level 1.",
      "lineage_hash": "f95327beaa7bd8eb1ca1dfbc569cb31da3a80fd15e7253617416fb2f4c19ec8a",
      "lineage_payload": {
        "cues": [
          "drag",
          "journal",
          "lock"
        ],
        "lesson_text": "ACTION: SEASON. Mechanism label: SUPPORTED_ROTATION. A stage wheel circles on a journal seat; drag rises and fine adjustment locks. Season SUPPORTED_ROTATION from microscope_stage_density_01 for Proof 036 level 1.",
        "mechanism": "SUPPORTED_ROTATION",
        "motifs": [
          "Rotation",
          "Support",
          "Friction",
          "Failure"
        ],
        "payload_hash": "34a8f512769d87b85a9ad0ac6992af5f44459b329e7f897dcf1ead9e4b708bf6",
        "request_id": "proof-036-level-1-season-017-supported_rotation",
        "source_refs": [
          "request",
          "context.summary"
        ]
      },
      "mechanism": "SUPPORTED_ROTATION",
      "motifs": [
        "Rotation",
        "Support",
        "Friction",
        "Failure"
      ],
      "record_id": "pond:supported_rotation:f95327beaa7bd8eb"
    }
  ],
  "schema_version": "inside_voice_mcp_pond_state.v1",
  "state_id": "inside_voice_mcp_local_pond",
  "updated_by_request_id": "proof-036-level-1-season-036-load_transfer"
}
